{"version":1,"resource":"vscode-remote://ssh-remote%2B52.2.116.225/home/rahul/rahul-apps/mynode-mongo-app/mongo_db.yaml","entries":[{"id":"DKmr.yaml","timestamp":1698316126451},{"id":"rJe3.yaml","timestamp":1698316158252},{"id":"5AuL.yaml","timestamp":1698316171688},{"id":"5FyO.yaml","timestamp":1698316759971},{"id":"wfp0.yaml","timestamp":1698316794943},{"id":"fyEV.yaml","timestamp":1698322821448},{"id":"IhEK.yaml","timestamp":1698322895061},{"id":"ukon.yaml","source":"undoRedo.source","timestamp":1698323457460}]}